examples/__init__.py
genotations/__init__.py
genotations/ensembl.py
genotations/genomes.py
genotations/intersections.py
genotations/primers.py
genotations/quantification.py
genotations-0.1.7.dist-info/METADATA
genotations-0.1.7.dist-info/WHEEL
genotations-0.1.7.dist-info/top_level.txt
genotations-0.1.7.dist-info/RECORD
