Metadata-Version: 2.1
Name: genotations
Version: 0.1.7
Summary: Genotations - python library to work with genomes and primers
Author: antonkulaga (Anton Kulaga)
Author-email: <antonkulaga@gmail.com>
Keywords: python,utils,files,genetics,ensembl,genomes,annotations
Classifier: Development Status :: 2 - Pre-Alpha
Classifier: Intended Audience :: Developers
Classifier: Programming Language :: Python :: 3.9
Classifier: Programming Language :: Python :: 3.10
Classifier: Programming Language :: Python :: 3.11
Classifier: Operating System :: Unix
Classifier: Operating System :: MacOS :: MacOS X
Classifier: Operating System :: Microsoft :: Windows
Requires-Dist: pyfunctional
Requires-Dist: more-itertools
Requires-Dist: click
Requires-Dist: pycomfort
Requires-Dist: polars
Requires-Dist: genomepy
Requires-Dist: primer3-py
Requires-Dist: pyarrow
Requires-Dist: loguru
